opendataschema/__init__.py
opendataschema/cli.py
opendataschema-0.6.0.dist-info/LICENSE
opendataschema-0.6.0.dist-info/METADATA
opendataschema-0.6.0.dist-info/WHEEL
opendataschema-0.6.0.dist-info/entry_points.txt
opendataschema-0.6.0.dist-info/top_level.txt
opendataschema-0.6.0.dist-info/zip-safe
opendataschema-0.6.0.dist-info/RECORD
