Metadata-Version: 2.1
Name: opendataschema
Version: 0.6.0
Summary: Open Data Schema catalog manipulation library
Home-page: https://framagit.org/opendataschema/opendataschema-python
Author: Pierre Dittgen
Author-email: pierre.dittgen@jailbreak.paris
License: MIT
Platform: UNKNOWN
Classifier: Development Status :: 4 - Beta
Classifier: Intended Audience :: Developers
Classifier: Topic :: Software Development :: Libraries :: Python Modules
Classifier: Operating System :: OS Independent
Classifier: License :: OSI Approved :: MIT License
Classifier: Programming Language :: Python :: 3
Requires-Dist: click
Requires-Dist: jsonschema
Requires-Dist: PyGithub
Requires-Dist: python-gitlab (>=1.8.0)
Requires-Dist: requests
